opentisim/__init__.py
opentisim/agribulk_defaults.py
opentisim/agribulk_mixins.py
opentisim/agribulk_objects.py
opentisim/agribulk_system.py
opentisim/container_defaults.py
opentisim/container_mixins.py
opentisim/container_objects.py
opentisim/container_system.py
opentisim/hydrogen_defaults.py
opentisim/hydrogen_mixins.py
opentisim/hydrogen_objects.py
opentisim/hydrogen_system.py
opentisim-0.5.0.dist-info/AUTHORS.rst
opentisim-0.5.0.dist-info/LICENSE.txt
opentisim-0.5.0.dist-info/METADATA
opentisim-0.5.0.dist-info/WHEEL
opentisim-0.5.0.dist-info/entry_points.txt
opentisim-0.5.0.dist-info/top_level.txt
opentisim-0.5.0.dist-info/RECORD
