Metadata-Version: 2.1
Name: opentisim
Version: 0.5.0
Summary: The OpenTISim package aims to facilitate adaptive terminal planning in the light of an uncertain future.
Home-page: https://github.com/TUDelft-CITG/OpenTISim
Author: Mark van Koningsveld
Author-email: m.vankoningsveld@tudelft.nl
License: mit
Keywords: OpenTISim
Platform: any
Classifier: Development Status :: 2 - Pre-Alpha
Classifier: Intended Audience :: Developers
Classifier: Natural Language :: English
Classifier: Programming Language :: Python :: 3
Requires-Dist: pandas (>=0.24.0)
Requires-Dist: numpy
Requires-Dist: scipy
Requires-Dist: matplotlib
Requires-Dist: pyproj
Requires-Dist: plotly
Requires-Dist: sphinx-rtd-theme
Provides-Extra: testing
Requires-Dist: pytest ; extra == 'testing'
Requires-Dist: pytest-cov ; extra == 'testing'
Requires-Dist: pytest-timeout ; extra == 'testing'
